{
  "best_distance": 29169.531,
  "best_solution": [
    234,
    235,
    236,
    233,
    232,
    230,
    241,
    243,
    276,
    0,
    257,
    256,
    9,
    263,
    181,
    95,
    139,
    173,
    138,
    152,
    176,
    61,
    124,
    119,
    81,
    116,
    164,
    105,
    117,
    41,
    59,
    98,
    172,
    104,
    149,
    201,
    32,
    154,
    115,
    274,
    70,
    177,
    212,
    223,
    93,
    222,
    204,
    63,
    196,
    100,
    171,
    150,
    71,
    75,
    161,
    225,
    143,
    252,
    266,
    165,
    107,
    178,
    142,
    151,
    58,
    111,
    275,
    114,
    125,
    180,
    44,
    42,
    134,
    269,
    209,
    25,
    40,
    183,
    102,
    122,
    26,
    155,
    271,
    259,
    136,
    79,
    135,
    251,
    33,
    193,
    34,
    270,
    68,
    65,
    194,
    73,
    216,
    197,
    215,
    202,
    90,
    221,
    198,
    170,
    184,
    168,
    62,
    108,
    97,
    109,
    264,
    249,
    244,
    246,
    239,
    238,
    228,
    206,
    272,
    36,
    205,
    87,
    56,
    103,
    220,
    219,
    94,
    167,
    131,
    186,
    218,
    78,
    38,
    265,
    76,
    268,
    83,
    13,
    261,
    106,
    191,
    127,
    278,
    242,
    231,
    1,
    17,
    211,
    169,
    72,
    174,
    189,
    262,
    273,
    158,
    69,
    210,
    86,
    77,
    82,
    54,
    227,
    66,
    15,
    137,
    226,
    207,
    190,
    5,
    141,
    20,
    67,
    2,
    55,
    21,
    240,
    163,
    120,
    182,
    112,
    74,
    160,
    277,
    237,
    121,
    39,
    129,
    50,
    35,
    247,
    179,
    29,
    10,
    175,
    47,
    192,
    208,
    188,
    91,
    3,
    147,
    96,
    49,
    23,
    6,
    260,
    113,
    118,
    27,
    4,
    14,
    18,
    16,
    245,
    258,
    166,
    157,
    229,
    37,
    255,
    253,
    130,
    24,
    214,
    185,
    43,
    153,
    128,
    64,
    12,
    101,
    279,
    48,
    84,
    156,
    250,
    8,
    187,
    60,
    52,
    267,
    203,
    92,
    53,
    110,
    140,
    217,
    199,
    46,
    89,
    28,
    51,
    132,
    57,
    126,
    31,
    144,
    45,
    7,
    80,
    11,
    162,
    133,
    145,
    254,
    248,
    99,
    88,
    224,
    213,
    200,
    195,
    22,
    123,
    148,
    19,
    146,
    85,
    159,
    30
  ],
  "distances": [
    29169.531
  ],
  "runtimes": [
    12
  ],
  "steps": [
    1011
  ],
  "evaluated": [
    18769
  ]
}