{
  "best_distance": 30535.646,
  "best_solution": [
    157,
    206,
    16,
    19,
    4,
    250,
    54,
    66,
    67,
    186,
    150,
    162,
    143,
    155,
    92,
    51,
    168,
    17,
    33,
    32,
    125,
    6,
    270,
    40,
    207,
    105,
    22,
    132,
    131,
    253,
    146,
    52,
    73,
    169,
    191,
    113,
    39,
    214,
    148,
    211,
    175,
    36,
    140,
    235,
    264,
    238,
    248,
    9,
    25,
    164,
    129,
    236,
    18,
    271,
    10,
    160,
    233,
    229,
    266,
    267,
    59,
    96,
    246,
    163,
    176,
    12,
    199,
    139,
    55,
    82,
    102,
    87,
    202,
    144,
    117,
    274,
    181,
    252,
    31,
    122,
    261,
    49,
    173,
    11,
    190,
    234,
    244,
    124,
    210,
    231,
    5,
    42,
    85,
    76,
    35,
    8,
    84,
    249,
    239,
    198,
    14,
    119,
    182,
    277,
    62,
    101,
    251,
    23,
    128,
    110,
    81,
    138,
    149,
    15,
    46,
    225,
    247,
    93,
    237,
    275,
    77,
    197,
    216,
    30,
    78,
    152,
    230,
    220,
    180,
    201,
    278,
    123,
    188,
    65,
    70,
    204,
    130,
    121,
    57,
    48,
    257,
    24,
    29,
    1,
    50,
    34,
    28,
    45,
    86,
    71,
    108,
    171,
    94,
    165,
    219,
    279,
    69,
    89,
    74,
    106,
    227,
    0,
    262,
    232,
    99,
    147,
    137,
    269,
    136,
    254,
    276,
    107,
    177,
    47,
    135,
    203,
    187,
    90,
    118,
    189,
    116,
    240,
    2,
    104,
    134,
    172,
    218,
    209,
    100,
    200,
    213,
    63,
    27,
    80,
    37,
    126,
    153,
    174,
    260,
    98,
    109,
    192,
    196,
    97,
    103,
    95,
    41,
    58,
    154,
    161,
    79,
    268,
    60,
    185,
    170,
    83,
    217,
    151,
    228,
    7,
    179,
    142,
    159,
    241,
    259,
    114,
    226,
    68,
    272,
    243,
    265,
    26,
    256,
    133,
    20,
    56,
    72,
    224,
    91,
    111,
    158,
    127,
    3,
    120,
    75,
    112,
    115,
    245,
    212,
    184,
    222,
    194,
    258,
    178,
    193,
    64,
    43,
    223,
    141,
    195,
    183,
    53,
    205,
    263,
    21,
    44,
    167,
    221,
    255,
    208,
    38,
    13,
    61,
    166,
    156,
    273,
    215,
    242,
    145,
    88
  ],
  "distances": [
    30535.646
  ],
  "runtimes": [
    591
  ],
  "steps": [
    0
  ],
  "evaluated": [
    2676
  ]
}